LICENSE
README.md
setup.py
test/test_planner.py
test/test_validator.py
test/test_warm_up.py
up_aries/__init__.py
up_aries/solver.py
up_aries.egg-info/PKG-INFO
up_aries.egg-info/SOURCES.txt
up_aries.egg-info/dependency_links.txt
up_aries.egg-info/requires.txt
up_aries.egg-info/top_level.txt
up_aries/bin/__init__.py
up_aries/bin/up-aries_linux_amd64
up_aries/bin/up-aries_macos_amd64
up_aries/bin/up-aries_macos_arm64
up_aries/bin/up-aries_windows_amd64.exe
up_aries/bin/up-aries_windows_arm64.exe